README.md
setup.py
PyPROPER.egg-info/PKG-INFO
PyPROPER.egg-info/SOURCES.txt
PyPROPER.egg-info/dependency_links.txt
PyPROPER.egg-info/requires.txt
PyPROPER.egg-info/top_level.txt
proper/__init__.py
proper/cubic_conv_c.c
proper/cubic_conv_threaded_c.c
proper/influence_dm5v2.fits
proper/libcconv.py
proper/libcconvthread.py
proper/libszoom.py
proper/prop_8th_order_mask.py
proper/prop_add_phase.py
proper/prop_add_wavefront.py
proper/prop_begin.py
proper/prop_circular_aperture.py
proper/prop_circular_obscuration.py
proper/prop_compile_c.py
proper/prop_cubic_conv.py
proper/prop_define_entrance.py
proper/prop_dftidefs.py
proper/prop_divide.py
proper/prop_dm.py
proper/prop_ellipse.py
proper/prop_elliptical_aperture.py
proper/prop_elliptical_obscuration.py
proper/prop_end.py
proper/prop_end_savestate.py
proper/prop_errormap.py
proper/prop_execute_multi.py
proper/prop_ffti.py
proper/prop_fftw.py
proper/prop_fftw_wisdom.py
proper/prop_fit_dm.py
proper/prop_fit_zernikes.py
proper/prop_fits_read.py
proper/prop_fits_write.py
proper/prop_get_amplitude.py
proper/prop_get_beamradius.py
proper/prop_get_distancetofocus.py
proper/prop_get_fratio.py
proper/prop_get_gridsize.py
proper/prop_get_nyquistsampling.py
proper/prop_get_phase.py
proper/prop_get_refradius.py
proper/prop_get_sampling.py
proper/prop_get_sampling_arcsec.py
proper/prop_get_sampling_radians.py
proper/prop_get_wavefront.py
proper/prop_get_wavelength.py
proper/prop_get_z.py
proper/prop_hex_wavefront.py
proper/prop_hex_zernikes.py
proper/prop_init_savestate.py
proper/prop_irregular_polygon.py
proper/prop_is_statesaved.py
proper/prop_lens.py
proper/prop_load_fftw_wisdom.py
proper/prop_magnify.py
proper/prop_multiply.py
proper/prop_noll_zernikes.py
proper/prop_pixellate.py
proper/prop_polygon.py
proper/prop_print_zernikes.py
proper/prop_propagate.py
proper/prop_psd_errormap.py
proper/prop_ptp.py
proper/prop_qphase.py
proper/prop_radius.py
proper/prop_readmap.py
proper/prop_rectangle.py
proper/prop_rectangular_aperture.py
proper/prop_rectangular_obscuration.py
proper/prop_resamplemap.py
proper/prop_rotate.py
proper/prop_rounded_rectangle.py
proper/prop_run.py
