Metadata-Version: 2.1
Name: PyPROPER
Version: 3.2.5
Summary: An optical wavefront propagation utility
Home-page: UNKNOWN
Author: Navtej Saini, Nikta Amiri, Luis Marchen
License: BSD
Platform: any
Provides-Extra: pyfftw
